pathlibutil/__init__.py
pathlibutil/base.py
pathlibutil/json.py
pathlibutil/path.py
pathlibutil/types.py
pathlibutil/urlpath.py
pathlibutil-0.3.6.dist-info/METADATA
pathlibutil-0.3.6.dist-info/WHEEL
pathlibutil-0.3.6.dist-info/licenses/LICENSE
pathlibutil-0.3.6.dist-info/RECORD
