Metadata-Version: 2.4
Name: pathlibutil
Version: 0.3.6
Summary: inherits from pathlib.Path with methods for hashing, copying, deleting and more
License: MIT
License-File: LICENSE
Keywords: pathlib,hashlib,shutil,urllib.parse,json,urlpath
Author: Christoph Dörrer
Author-email: d-chris@web.de
Requires-Python: >=3.8.1,<4.0.0
Classifier: License :: OSI Approved :: MIT License
Classifier: Operating System :: OS Independent
Classifier: Programming Language :: Python :: 3
Classifier: Programming Language :: Python :: 3.9
Classifier: Programming Language :: Python :: 3.10
Classifier: Programming Language :: Python :: 3.11
Classifier: Programming Language :: Python :: 3.12
Classifier: Programming Language :: Python :: 3.13
Classifier: Programming Language :: Python :: 3.14
Classifier: Programming Language :: Python :: 3.8
Provides-Extra: 7z
Requires-Dist: py7zr (>=0.20.2) ; extra == "7z"
Project-URL: documentation, https://d-chris.github.io/pathlibutil
Project-URL: repository, https://github.com/d-chris/pathlibutil
